cloudera_assist/__init__.py
cloudera_assist/__main__.py
cloudera_assist/__version__.py
cloudera_assist/cli.py
cloudera_assist/commands.py
cloudera_assist/components.py
cloudera_assist/config.py
cloudera_assist/credentials.py
cloudera_assist/env.py
cloudera_assist-0.1.0.dist-info/METADATA
cloudera_assist-0.1.0.dist-info/WHEEL
cloudera_assist-0.1.0.dist-info/entry_points.txt
cloudera_assist-0.1.0.dist-info/licenses/LICENSE
cloudera_assist-0.1.0.dist-info/RECORD
