Metadata-Version: 2.4
Name: cloudera-assist
Version: 0.1.0
Summary: A CLI tool for managing credentials and executing playbooks for Cloudera demonstrations, workshops, and tutorials.
Project-URL: Documentation, https://github.com/cloudera-labs/cloudera-assist
Project-URL: Source Code, https://github.com/cloudera-labs/cloudera-assist
Author-email: "Cloudera, Inc." <cloudera-labs@cloudera.com>
License-Expression: Apache-2.0
License-File: LICENSE
Keywords: ansible-navigator,cdp,cloudera
Classifier: Development Status :: 4 - Beta
Classifier: Environment :: Console
Classifier: Framework :: AWS CDK
Classifier: Framework :: Ansible
Classifier: Intended Audience :: End Users/Desktop
Classifier: License :: OSI Approved :: Apache Software License
Classifier: Operating System :: MacOS
Classifier: Operating System :: Microsoft :: Windows
Classifier: Operating System :: POSIX :: Linux
Classifier: Programming Language :: Python
Classifier: Programming Language :: Python :: 3
Requires-Python: >=3.9
Requires-Dist: click>=8.0.0
Requires-Dist: cryptography>=43.0.0
Requires-Dist: python-dotenv>=1.0.1
Requires-Dist: pyyaml>=6.0.0
Requires-Dist: rich>=13.0.0
